{
    "prepare_queue": {
        "installed": [],
        "uninstalled": []
    },
    "config_munge": {
        "files": {
            "config.xml": {
                "parents": {
                    "/*": [
                        {
                            "xml": "<access origin=\"https://m.facebook.com\" />",
                            "count": 1
                        },
                        {
                            "xml": "<access origin=\"https://graph.facebook.com\" />",
                            "count": 1
                        },
                        {
                            "xml": "<access origin=\"https://api.facebook.com\" />",
                            "count": 1
                        },
                        {
                            "xml": "<access origin=\"https://*.fbcdn.net\" />",
                            "count": 1
                        },
                        {
                            "xml": "<access origin=\"https://*.akamaihd.net\" />",
                            "count": 1
                        }
                    ]
                }
            },
            "res/xml/config.xml": {
                "parents": {
                    "plugins": [
                        {
                            "xml": "<plugin name=\"Update\" value=\"org.common.plugins.updateapp.Update\" />",
                            "count": 1
                        }
                    ],
                    "/*": [
                        {
                            "xml": "<feature name=\"NetworkStatus\"><param name=\"android-package\" value=\"org.apache.cordova.networkinformation.NetworkManager\" /></feature>",
                            "count": 1
                        },
                        {
                            "xml": "<feature name=\"Device\"><param name=\"android-package\" value=\"org.apache.cordova.device.Device\" /></feature>",
                            "count": 1
                        }
                    ]
                }
            },
            "AndroidManifest.xml": {
                "parents": {
                    "/*": [
                        {
                            "xml": "<uses-permission android:name=\"android.permission.ACCESS_NETWORK_STATE\" />",
                            "count": 1
                        }
                    ]
                }
            }
        }
    },
    "installed_plugins": {
        "org.common.plugins.updateapp": {
            "PACKAGE_NAME": "io.popcorntime.frontend"
        },
        "org.apache.cordova.network-information": {
            "PACKAGE_NAME": "io.popcorntime.frontend"
        },
        "org.apache.cordova.device": {
            "PACKAGE_NAME": "io.popcorntime.frontend"
        }
    },
    "dependent_plugins": {}
}